README.md
torgo/__init__.py
torgo/torgo.py
torgo-0.1.2.dist-info/entry_points.txt
torgo-0.1.2.dist-info/WHEEL
torgo-0.1.2.dist-info/METADATA
torgo-0.1.2.dist-info/RECORD
