Metadata-Version: 2.1
Name: torgo
Version: 0.1.2
Summary: The system-wide Org file manager
Home-page: https://github.com/criswell/torgo
License: AGPL-3.0
Author: Sam Hart
Author-email: hartsn@gmail.com
Requires-Python: >=3.6,<4.0
Classifier: License :: OSI Approved :: GNU Affero General Public License v3
Classifier: Programming Language :: Python :: 3
Classifier: Programming Language :: Python :: 3.6
Classifier: Programming Language :: Python :: 3.7
Classifier: Programming Language :: Python :: 3.8
Requires-Dist: argparse (>=1.4.0,<2.0.0)
Requires-Dist: colorama (>=0.4.3,<0.5.0)
Requires-Dist: configparser (>=5.0.0,<6.0.0)
Requires-Dist: pathlib (>=1.0.1,<2.0.0)
Requires-Dist: tinydb (>=3.15.2,<4.0.0)
